odoo/addons/l10n_es_verifactu_oca/README.rst
odoo/addons/l10n_es_verifactu_oca/__init__.py
odoo/addons/l10n_es_verifactu_oca/__manifest__.py
odoo/addons/l10n_es_verifactu_oca/hooks.py
odoo/addons/l10n_es_verifactu_oca/data/ir_config_parameter.xml
odoo/addons/l10n_es_verifactu_oca/data/ir_cron.xml
odoo/addons/l10n_es_verifactu_oca/data/l10n.es.aeat.map.tax.line.tax.csv
odoo/addons/l10n_es_verifactu_oca/data/mail_activity_data.xml
odoo/addons/l10n_es_verifactu_oca/data/neutralize.sql
odoo/addons/l10n_es_verifactu_oca/data/verifactu.map.csv
odoo/addons/l10n_es_verifactu_oca/data/verifactu.map.line.csv
odoo/addons/l10n_es_verifactu_oca/data/verifactu_registration_key_data.xml
odoo/addons/l10n_es_verifactu_oca/data/verifactu_tax_agency_data.xml
odoo/addons/l10n_es_verifactu_oca/data/template/account.fiscal.position-es_common.csv
odoo/addons/l10n_es_verifactu_oca/i18n/ca.po
odoo/addons/l10n_es_verifactu_oca/i18n/ca_ES.po
odoo/addons/l10n_es_verifactu_oca/i18n/es.po
odoo/addons/l10n_es_verifactu_oca/i18n/l10n_es_verifactu_oca.pot
odoo/addons/l10n_es_verifactu_oca/migrations/18.0.1.1.0/pre-migration.py
odoo/addons/l10n_es_verifactu_oca/models/__init__.py
odoo/addons/l10n_es_verifactu_oca/models/account_chart_template.py
odoo/addons/l10n_es_verifactu_oca/models/account_fiscal_position.py
odoo/addons/l10n_es_verifactu_oca/models/account_journal.py
odoo/addons/l10n_es_verifactu_oca/models/account_move.py
odoo/addons/l10n_es_verifactu_oca/models/aeat_tax_agency.py
odoo/addons/l10n_es_verifactu_oca/models/res_company.py
odoo/addons/l10n_es_verifactu_oca/models/res_partner.py
odoo/addons/l10n_es_verifactu_oca/models/verifactu_chaining.py
odoo/addons/l10n_es_verifactu_oca/models/verifactu_developer.py
odoo/addons/l10n_es_verifactu_oca/models/verifactu_invoice_entry.py
odoo/addons/l10n_es_verifactu_oca/models/verifactu_invoice_entry_response.py
odoo/addons/l10n_es_verifactu_oca/models/verifactu_invoice_entry_response_line.py
odoo_addon_l10n_es_verifactu_oca-18.0.1.2.2.dist-info/METADATA
odoo_addon_l10n_es_verifactu_oca-18.0.1.2.2.dist-info/WHEEL
odoo_addon_l10n_es_verifactu_oca-18.0.1.2.2.dist-info/top_level.txt
odoo_addon_l10n_es_verifactu_oca-18.0.1.2.2.dist-info/RECORD
