Metadata-Version: 2.1
Name: odoo-addon-l10n_es_verifactu_oca
Version: 18.0.1.2.2
Requires-Python: >=3.10
Requires-Dist: odoo-addon-account_invoice_refund_link==18.0.*
Requires-Dist: odoo-addon-l10n_es_aeat==18.0.*
Requires-Dist: odoo==18.0.*
Summary: =?utf-8?q?Comunicaci=C3=B3n_VERI*FACTU?=
Home-page: https://github.com/OCA/l10n-spain
License: AGPL-3
Author: Aures Tic,ForgeFlow,Tecnativa,Factor Libre,Odoo Community Association (OCA)
Author-email: support@odoo-community.org
Classifier: Programming Language :: Python
Classifier: Framework :: Odoo
Classifier: Framework :: Odoo :: 18.0
Classifier: License :: OSI Approved :: GNU Affero General Public License v3
